topsis_anshika_102303042/__init__.py
topsis_anshika_102303042/topsis.py
topsis_anshika_102303042-0.0.2.dist-info/licenses/LICENSE
topsis_anshika_102303042-0.0.2.dist-info/METADATA
topsis_anshika_102303042-0.0.2.dist-info/WHEEL
topsis_anshika_102303042-0.0.2.dist-info/entry_points.txt
topsis_anshika_102303042-0.0.2.dist-info/top_level.txt
topsis_anshika_102303042-0.0.2.dist-info/RECORD
