Metadata-Version: 2.4
Name: Topsis-Anshika-102303042
Version: 0.0.2
Summary: A Python package for TOPSIS implementation
Author: Anshika
Author-email: anshika.aggarwal05@gmail.com
License-File: LICENSE
Requires-Dist: pandas
Requires-Dist: numpy
Dynamic: author
Dynamic: author-email
Dynamic: description
Dynamic: description-content-type
Dynamic: license-file
Dynamic: requires-dist
Dynamic: summary
